oct2py/__init__.py
oct2py/_pyeval.m
oct2py/_version.py
oct2py/core.py
oct2py/demo.py
oct2py/dynamic.py
oct2py/io.py
oct2py/speed_check.py
oct2py/thread_check.py
oct2py/utils.py
oct2py/ipython/__init__.py
oct2py/ipython/ipython-COPYING.txt
oct2py/ipython/octavemagic.py
oct2py-5.7.1.dist-info/METADATA
oct2py-5.7.1.dist-info/WHEEL
oct2py-5.7.1.dist-info/licenses/LICENSE.txt
oct2py-5.7.1.dist-info/RECORD
