Metadata-Version: 2.3
Name: oct2py
Version: 5.7.1
Summary: 'Python to GNU Octave bridge --> run m-files from python.'
Project-URL: homepage, https://github.com/blink1073/oct2py
Project-URL: documentation, https://blink1073.github.io/oct2py
Author-email: Steven Silvester <steven.silvester@ieee.org>
License: MIT
License-File: LICENSE.txt
Classifier: Development Status :: 5 - Production/Stable
Classifier: Intended Audience :: Developers
Classifier: Intended Audience :: Science/Research
Classifier: License :: OSI Approved :: MIT License
Classifier: Operating System :: OS Independent
Classifier: Programming Language :: Python
Classifier: Programming Language :: Python :: 3
Classifier: Topic :: Scientific/Engineering
Classifier: Topic :: Software Development
Requires-Python: >=3.8
Requires-Dist: numpy>=1.12
Requires-Dist: octave-kernel>=0.34.0
Requires-Dist: scipy>=0.17
Provides-Extra: docs
Requires-Dist: myst-parser; extra == 'docs'
Requires-Dist: pydata-sphinx-theme; extra == 'docs'
Requires-Dist: sphinx; extra == 'docs'
Requires-Dist: sphinxcontrib-spelling; extra == 'docs'
Provides-Extra: test
Requires-Dist: nbconvert; extra == 'test'
Requires-Dist: pandas; extra == 'test'
Requires-Dist: pre-commit; extra == 'test'
Requires-Dist: pytest-timeout; extra == 'test'
Requires-Dist: pytest<8; extra == 'test'
